jobshop.cpython-312-x86_64-linux-gnu.so
jobshop.libs/libGLdispatch-64b28464.so.0.0.0
jobshop.libs/libOpenGL-4c5f8d52.so.0.0.0
jobshop.libs/libGLU-ff1477cc.so.1.3.1
jobshop.libs/libGLX-c14481bc.so.0.0.0
jobshop-0.1.0.dist-info/top_level.txt
jobshop-0.1.0.dist-info/RECORD
jobshop-0.1.0.dist-info/LICENSE
jobshop-0.1.0.dist-info/METADATA
jobshop-0.1.0.dist-info/WHEEL
