Metadata-Version: 2.1
Name: jobshop
Version: 0.1.0
Summary: Job Shop Scheduling Algorithms
Author: Per-Arne Andersen
Author-email: Per-Arne Andersen <per@sysx.no>
License: Copyright 2024 Per-Arne Andersen
Project-URL: Homepage, https://github.com/cair/jobshop
Project-URL: Bug Tracker, https://github.com/cair/jobshop/issues
Classifier: Programming Language :: Python :: 3
Classifier: License :: OSI Approved :: MIT License
Classifier: Operating System :: OS Independent
Requires-Python: >=3.10
License-File: LICENSE
